{
    "map": {
        "name": "Bombman",
        "filename": "level2.json",
        "height": 2240,
        "width": 1610,
        "id": 2,
        "obstacles": [
            {
                "x": 315,
                "y": 245,
                "type": 1
            },
            {
                "x": 385,
                "y": 245,
                "type": 1
            },
            {
                "x": 455,
                "y": 245,
                "type": 1
            },
            {
                "x": 455,
                "y": 315,
                "type": 1
            },
            {
                "x": 525,
                "y": 315,
                "type": 1
            },
            {
                "x": 595,
                "y": 315,
                "type": 1
            },
            {
                "x": 665,
                "y": 315,
                "type": 1
            },
            {
                "x": 735,
                "y": 315,
                "type": 1
            },
            {
                "x": 805,
                "y": 315,
                "type": 1
            },
            {
                "x": 875,
                "y": 315,
                "type": 1
            },
            {
                "x": 945,
                "y": 315,
                "type": 1
            },
            {
                "x": 1015,
                "y": 315,
                "type": 1
            },
            {
                "x": 1015,
                "y": 245,
                "type": 1
            },
            {
                "x": 1085,
                "y": 245,
                "type": 1
            },
            {
                "x": 1155,
                "y": 245,
                "type": 1
            },
            {
                "x": 1225,
                "y": 245,
                "type": 1
            },
            {
                "x": 1295,
                "y": 245,
                "type": 1
            },
            {
                "x": 1365,
                "y": 245,
                "type": 1
            },
            {
                "x": 1645,
                "y": 245,
                "type": 1
            },
            {
                "x": 1365,
                "y": 315,
                "type": 1
            },
            {
                "x": 1365,
                "y": 385,
                "type": 1
            },
            {
                "x": 1645,
                "y": 315,
                "type": 1
            },
            {
                "x": 1645,
                "y": 385,
                "type": 1
            },
            {
                "x": 1645,
                "y": 455,
                "type": 1
            },
            {
                "x": 1365,
                "y": 455,
                "type": 1
            },
            {
                "x": 1365,
                "y": 525,
                "type": 1
            },
            {
                "x": 1645,
                "y": 525,
                "type": 1
            },
            {
                "x": 1645,
                "y": 595,
                "type": 1
            },
            {
                "x": 1365,
                "y": 595,
                "type": 1
            },
            {
                "x": 1365,
                "y": 665,
                "type": 2
            },
            {
                "x": 1645,
                "y": 735,
                "type": 2
            },
            {
                "x": 1365,
                "y": 735,
                "type": 2
            },
            {
                "x": 1365,
                "y": 805,
                "type": 2
            },
            {
                "x": 1365,
                "y": 875,
                "type": 2
            },
            {
                "x": 1645,
                "y": 805,
                "type": 2
            },
            {
                "x": 1645,
                "y": 875,
                "type": 2
            },
            {
                "x": 1645,
                "y": 945,
                "type": 2
            },
            {
                "x": 1645,
                "y": 1015,
                "type": 2
            },
            {
                "x": 1645,
                "y": 1085,
                "type": 2
            },
            {
                "x": 1645,
                "y": 1155,
                "type": 2
            },
            {
                "x": 1645,
                "y": 665,
                "type": 1
            },
            {
                "x": 1155,
                "y": 1155,
                "type": 3
            },
            {
                "x": 1085,
                "y": 1155,
                "type": 3
            },
            {
                "x": 1015,
                "y": 1155,
                "type": 3
            },
            {
                "x": 945,
                "y": 1155,
                "type": 3
            },
            {
                "x": 945,
                "y": 1085,
                "type": 3
            },
            {
                "x": 875,
                "y": 1085,
                "type": 3
            },
            {
                "x": 805,
                "y": 1085,
                "type": 3
            },
            {
                "x": 735,
                "y": 1085,
                "type": 3
            },
            {
                "x": 665,
                "y": 1085,
                "type": 3
            },
            {
                "x": 595,
                "y": 1085,
                "type": 3
            },
            {
                "x": 525,
                "y": 1085,
                "type": 3
            },
            {
                "x": 455,
                "y": 1085,
                "type": 3
            },
            {
                "x": 385,
                "y": 1085,
                "type": 3
            },
            {
                "x": 315,
                "y": 1085,
                "type": 3
            },
            {
                "x": 1295,
                "y": 875,
                "type": 2
            },
            {
                "x": 1225,
                "y": 875,
                "type": 2
            },
            {
                "x": 1155,
                "y": 875,
                "type": 2
            },
            {
                "x": 1155,
                "y": 805,
                "type": 2
            },
            {
                "x": 1085,
                "y": 805,
                "type": 2
            },
            {
                "x": 1015,
                "y": 805,
                "type": 2
            },
            {
                "x": 945,
                "y": 805,
                "type": 2
            },
            {
                "x": 875,
                "y": 805,
                "type": 2
            },
            {
                "x": 805,
                "y": 805,
                "type": 2
            },
            {
                "x": 735,
                "y": 805,
                "type": 2
            },
            {
                "x": 665,
                "y": 805,
                "type": 2
            },
            {
                "x": 595,
                "y": 805,
                "type": 2
            },
            {
                "x": 525,
                "y": 805,
                "type": 2
            },
            {
                "x": 455,
                "y": 805,
                "type": 2
            },
            {
                "x": 385,
                "y": 805,
                "type": 2
            },
            {
                "x": 315,
                "y": 805,
                "type": 2
            },
            {
                "x": 245,
                "y": 805,
                "type": 2
            },
            {
                "x": 175,
                "y": 805,
                "type": 2
            },
            {
                "x": 105,
                "y": 805,
                "type": 2
            },
            {
                "x": 35,
                "y": 805,
                "type": 2
            },
            {
                "x": 35,
                "y": 875,
                "type": 3
            },
            {
                "x": 35,
                "y": 945,
                "type": 3
            },
            {
                "x": 35,
                "y": 1015,
                "type": 3
            },
            {
                "x": 35,
                "y": 1085,
                "type": 3
            },
            {
                "x": 35,
                "y": 1155,
                "type": 3
            },
            {
                "x": 35,
                "y": 1225,
                "type": 3
            },
            {
                "x": 35,
                "y": 1295,
                "type": 3
            },
            {
                "x": 35,
                "y": 1365,
                "type": 3
            },
            {
                "x": 35,
                "y": 1435,
                "type": 3
            },
            {
                "x": 35,
                "y": 1505,
                "type": 3
            },
            {
                "x": 35,
                "y": 1575,
                "type": 3
            },
            {
                "x": 35,
                "y": 1645,
                "type": 3
            },
            {
                "x": 35,
                "y": 1715,
                "type": 3
            },
            {
                "x": 35,
                "y": 1785,
                "type": 3
            },
            {
                "x": 35,
                "y": 1925,
                "type": 3
            },
            {
                "x": 35,
                "y": 2065,
                "type": 3
            },
            {
                "x": 35,
                "y": 1995,
                "type": 3
            },
            {
                "x": 35,
                "y": 1855,
                "type": 3
            },
            {
                "x": 315,
                "y": 1155,
                "type": 3
            },
            {
                "x": 315,
                "y": 1225,
                "type": 3
            },
            {
                "x": 315,
                "y": 1295,
                "type": 3
            },
            {
                "x": 315,
                "y": 1365,
                "type": 3
            },
            {
                "x": 315,
                "y": 1435,
                "type": 3
            },
            {
                "x": 315,
                "y": 1505,
                "type": 3
            },
            {
                "x": 315,
                "y": 1575,
                "type": 3
            },
            {
                "x": 315,
                "y": 1645,
                "type": 3
            },
            {
                "x": 315,
                "y": 1715,
                "type": 3
            },
            {
                "x": 315,
                "y": 1785,
                "type": 3
            },
            {
                "x": 35,
                "y": 2135,
                "type": 4
            },
            {
                "x": 105,
                "y": 2135,
                "type": 4
            },
            {
                "x": 175,
                "y": 2135,
                "type": 4
            },
            {
                "x": 245,
                "y": 2135,
                "type": 4
            },
            {
                "x": 315,
                "y": 2135,
                "type": 4
            },
            {
                "x": 385,
                "y": 2135,
                "type": 4
            },
            {
                "x": 455,
                "y": 2135,
                "type": 4
            },
            {
                "x": 525,
                "y": 2135,
                "type": 4
            },
            {
                "x": 315,
                "y": 1855,
                "type": 4
            },
            {
                "x": 385,
                "y": 1855,
                "type": 4
            },
            {
                "x": 455,
                "y": 1855,
                "type": 4
            },
            {
                "x": 525,
                "y": 1855,
                "type": 4
            },
            {
                "x": 595,
                "y": 1855,
                "type": 4
            },
            {
                "x": 665,
                "y": 1855,
                "type": 4
            },
            {
                "x": 735,
                "y": 1855,
                "type": 4
            },
            {
                "x": 805,
                "y": 1855,
                "type": 4
            },
            {
                "x": 875,
                "y": 1855,
                "type": 4
            },
            {
                "x": 945,
                "y": 1855,
                "type": 4
            },
            {
                "x": 525,
                "y": 2205,
                "type": 4
            },
            {
                "x": 525,
                "y": 2275,
                "type": 4
            },
            {
                "x": 595,
                "y": 2275,
                "type": 4
            },
            {
                "x": 665,
                "y": 2275,
                "type": 4
            },
            {
                "x": 735,
                "y": 2275,
                "type": 4
            },
            {
                "x": 805,
                "y": 2275,
                "type": 4
            },
            {
                "x": 875,
                "y": 2275,
                "type": 4
            },
            {
                "x": 945,
                "y": 2275,
                "type": 4
            },
            {
                "x": 1015,
                "y": 2275,
                "type": 4
            },
            {
                "x": 595,
                "y": 2205,
                "type": 5
            },
            {
                "x": 665,
                "y": 2205,
                "type": 5
            },
            {
                "x": 735,
                "y": 2205,
                "type": 5
            },
            {
                "x": 1085,
                "y": 2275,
                "type": 4
            },
            {
                "x": 1085,
                "y": 2205,
                "type": 4
            },
            {
                "x": 1155,
                "y": 2205,
                "type": 4
            },
            {
                "x": 1225,
                "y": 2205,
                "type": 4
            },
            {
                "x": 1225,
                "y": 2135,
                "type": 4
            },
            {
                "x": 1295,
                "y": 2135,
                "type": 4
            },
            {
                "x": 1365,
                "y": 2135,
                "type": 4
            },
            {
                "x": 1435,
                "y": 2135,
                "type": 4
            },
            {
                "x": 1505,
                "y": 2135,
                "type": 4
            },
            {
                "x": 1575,
                "y": 2135,
                "type": 4
            },
            {
                "x": 1645,
                "y": 2135,
                "type": 4
            },
            {
                "x": 1645,
                "y": 2065,
                "type": 4
            },
            {
                "x": 1645,
                "y": 1995,
                "type": 4
            },
            {
                "x": 1645,
                "y": 1925,
                "type": 4
            },
            {
                "x": 1645,
                "y": 1855,
                "type": 4
            },
            {
                "x": 1575,
                "y": 1855,
                "type": 4
            },
            {
                "x": 1505,
                "y": 1855,
                "type": 4
            },
            {
                "x": 1435,
                "y": 1855,
                "type": 4
            },
            {
                "x": 1365,
                "y": 1855,
                "type": 4
            },
            {
                "x": 1295,
                "y": 1855,
                "type": 4
            },
            {
                "x": 1155,
                "y": 1855,
                "type": 4
            },
            {
                "x": 1225,
                "y": 1855,
                "type": 4
            },
            {
                "x": 1085,
                "y": 1855,
                "type": 4
            },
            {
                "x": 1015,
                "y": 1855,
                "type": 4
            },
            {
                "x": 1225,
                "y": 2065,
                "type": 10
            },
            {
                "x": 1085,
                "y": 2135,
                "type": 10
            },
            {
                "x": 1015,
                "y": 2205,
                "type": 12
            },
            {
                "x": 525,
                "y": 2065,
                "type": 12
            },
            {
                "x": 315,
                "y": 1015,
                "type": 12
            },
            {
                "x": 245,
                "y": 945,
                "type": 9
            },
            {
                "x": 175,
                "y": 945,
                "type": 9
            },
            {
                "x": 105,
                "y": 945,
                "type": 9
            },
            {
                "x": 1155,
                "y": 1015,
                "type": 9
            },
            {
                "x": 945,
                "y": 1015,
                "type": 12
            },
            {
                "x": 1575,
                "y": 1155,
                "type": 12
            },
            {
                "x": 1435,
                "y": 105,
                "type": 9
            },
            {
                "x": 1155,
                "y": 175,
                "type": 10
            },
            {
                "x": 945,
                "y": 245,
                "type": 12
            },
            {
                "x": 455,
                "y": 175,
                "type": 11
            },
            {
                "x": 1645,
                "y": 1225,
                "type": 2
            },
            {
                "x": 1575,
                "y": 1225,
                "type": 2
            },
            {
                "x": 1365,
                "y": 1225,
                "type": 2
            },
            {
                "x": 1295,
                "y": 1225,
                "type": 2
            },
            {
                "x": 1225,
                "y": 1225,
                "type": 2
            },
            {
                "x": 1155,
                "y": 1225,
                "type": 2
            },
            {
                "x": 1435,
                "y": 1225,
                "type": 6
            },
            {
                "x": 1505,
                "y": 1225,
                "type": 6
            },
            {
                "x": 105,
                "y": 175,
                "type": 8
            },
            {
                "x": 35,
                "y": 175,
                "type": 4
            },
            {
                "x": 35,
                "y": 105,
                "type": 4
            },
            {
                "x": 175,
                "y": 245,
                "type": 4
            },
            {
                "x": 105,
                "y": 245,
                "type": 4
            },
            {
                "x": 35,
                "y": 245,
                "type": 4
            },
            {
                "x": 245,
                "y": 245,
                "type": 4
            },
            {
                "x": 245,
                "y": 175,
                "type": 4
            }
        ]
    }
}
